[
  {
    "logo_url": "img/profile-icons/worker-0.jpg",
    "title": "Менеджер",
    "type": "resume",
    "price": 1000,
    "city_list": [
      "Нижний Новгород",
      "Самара"
    ],
    "links": [
      {
        "text": "my custom link to website sdfdsfd",
        "url": "https://google.com"
      },
      {
        "text": "quick fox jumps over lazy dog",
        "url": "https://google.com"
      },
      {
        "text": "one two three four",
        "url": "https://google.com"
      }
    ],
    "views": 100500,
    "favourites": 100,
    "dialogs": 30,
    "responses": 20,
    "matching_vacancies": 42,
    "days_published": 1,
    "services": [
      {
        "id": 0,
        "date_from": "11.05.2022",
        "date_to": "11.06.2022"
      },
      {
        "id": 1,
        "date_from": "11.05.2022",
        "date_to": "11.06.2022"
      },
      {
        "id": 2,
        "date_from": "11.05.2022",
        "date_to": "11.06.2022"
      }
    ]
  }
]